{
  "generatedAt": "2026-07-23T22:17:42Z",
  "sampleCounts": {
    "track": 4338,
    "formation": 2676,
    "birth_features": 2097,
    "intensity": 12641,
    "intensify": 2464,
    "demise": 4946,
    "track_sample_events": 15838,
    "withSurfaceDbz": 12091,
    "withFct": 4790,
    "withFreezingLevel": 15838,
    "withHailProxy": 182,
    "total": 29162
  },
  "readyForApply": true,
  "proposals": [
    {
      "param": "MAX_WIND_ALIGN_DEG",
      "current": 35,
      "proposed": 40,
      "confidence": "high",
      "reason": "minimum blended median errKm T+15 podle windAlignDeg",
      "n": 721,
      "evidence": [
        {
          "thr": 20,
          "nRadarLike": 369,
          "nWindLike": 352,
          "medErrRadarLike": 15.0,
          "medErrWindLike": 13.62,
          "blendScore": 14.33
        },
        {
          "thr": 25,
          "nRadarLike": 417,
          "nWindLike": 304,
          "medErrRadarLike": 15.28,
          "medErrWindLike": 13.34,
          "blendScore": 14.46
        },
        {
          "thr": 30,
          "nRadarLike": 452,
          "nWindLike": 269,
          "medErrRadarLike": 15.19,
          "medErrWindLike": 13.27,
          "blendScore": 14.47
        },
        {
          "thr": 35,
          "nRadarLike": 474,
          "nWindLike": 247,
          "medErrRadarLike": 14.97,
          "medErrWindLike": 13.25,
          "blendScore": 14.38
        },
        {
          "thr": 40,
          "nRadarLike": 493,
          "nWindLike": 228,
          "medErrRadarLike": 14.61,
          "medErrWindLike": 12.68,
          "blendScore": 14.0
        },
        {
          "thr": 45,
          "nRadarLike": 510,
          "nWindLike": 211,
          "medErrRadarLike": 14.54,
          "medErrWindLike": 13.4,
          "blendScore": 14.21
        },
        {
          "thr": 55,
          "nRadarLike": 530,
          "nWindLike": 191,
          "medErrRadarLike": 14.73,
          "medErrWindLike": 12.58,
          "blendScore": 14.16
        }
      ]
    },
    {
      "param": "MAX_SEGMENT_JITTER_DEG",
      "current": 55,
      "proposed": 55,
      "confidence": "medium",
      "n": 4112,
      "p85Jitter": 126.0,
      "reason": "p85 segmentJitter u rozumných rychlostí"
    },
    {
      "param": "TRUE_BIRTH_MAX_DBZ",
      "current": 39,
      "proposed": 40,
      "also": {
        "TRUE_BIRTH_MAX_AGE_MIN": {
          "current": 10,
          "proposed": 10
        }
      },
      "confidence": "medium",
      "n": 2097,
      "medianBirthDbzTrue": 37.0,
      "medianBirthDbzFalse": 43.0,
      "reason": "oddělení trueBirth vs příjezd podle birthDbz"
    },
    {
      "param": "MIN_ZONE_SCORE",
      "current": 28,
      "proposed": 28,
      "confidence": "low",
      "n": 2676,
      "nUsable": 339,
      "nHit": 339,
      "nMiss": 0,
      "reason": "málo ověřených miss (timeouty nepočítat) — práh nedržet z F1"
    },
    {
      "param": "SPEED_BIAS_KMH",
      "proposed": 0,
      "confidence": "low",
      "n": 0,
      "reason": "málo speedErr samples"
    },
    {
      "param": "FCT_AGREE_MAX_DEG",
      "current": 35,
      "proposed": 35,
      "confidence": "low",
      "n": 0,
      "file": "scripts/chmi_radar.py + src/storm/radarCells.ts",
      "reason": "málo track samples s FCT (sběr ČHMÚ Fáze 3)"
    },
    {
      "param": "intensification.alertScoreMin",
      "current": 50,
      "proposed": 50,
      "confidence": "high",
      "n": 2464,
      "hitRate": 0.389,
      "nHit": 959,
      "nMiss": 1505,
      "file": "src/storm/config.ts",
      "reason": "hit rate 39% — držet",
      "alsoReview": {
        "param": "intensification.suppressIfGrowthDbzBelow",
        "current": 2,
        "hint": "při fade po purple zkontroluj růst dBZ před kandidátem"
      }
    },
    {
      "param": "active.hail.minAboveFreezingKm",
      "current": 1.5,
      "proposed": 1.5,
      "confidence": "medium",
      "n": 26,
      "nHailEvents": 182,
      "shortFadeShare": 0.0,
      "file": "src/storm/config.ts",
      "reason": "zatím držet; ladit až s víc bouřkami",
      "alsoReview": {
        "param": "active.hail.likelyDbz",
        "current": 55
      }
    },
    {
      "param": "evolution.trendGain",
      "current": 0.55,
      "proposed": 0.65,
      "confidence": "high",
      "n": 12641,
      "medianBiasDbz": 3.9,
      "medianAbsErrDbz": 6.5,
      "file": "src/storm/config.ts (evolution) + ACTIVE_CONSTANTS emit_learning",
      "reason": "median bias +3.9 dBZ (podhodnocení) → vyšší trendGain",
      "alsoReview": {
        "param": "evolution.blendTrend",
        "current": 0.45,
        "hint": "při velké MAE doladit váhu growth vs slope",
        "footprint": {
          "param": "evolution.footprintPerDbz",
          "current": 0.01,
          "proposed": 0.013,
          "n": 5207,
          "medianScaleBias": 0.086,
          "hint": "kladný = stopa roste víc než predikce"
        }
      }
    }
  ],
  "intensity": {
    "n": 12641,
    "medianAbsErrDbz": 7.0,
    "medianAbsErrEvolveDbz": 6.5,
    "nWithEvolve": 12641,
    "hint": "errEvolveDbz ladí stormConfig.evolution; slope errDbz je baseline"
  },
  "intensifyPurple": {
    "n": 2464,
    "hitRate": 0.389,
    "hint": "upřímná fialová — nízký hitRate → vyšší alertScoreMin / suppress"
  },
  "demise": {
    "n": 4946,
    "reasons": {
      "merge_or_jump": 4693,
      "fade": 253
    },
    "medianLifeMin": 0.0,
    "medianFadeLifeMin": 0.0,
    "nFade": 253,
    "nWithHailProxy": 26,
    "nAfterPurple": 236,
    "hint": "medianLifeMin je zkreslené merge_or_jump — ber medianFadeLifeMin"
  },
  "applyHint": "Po review propsat: src/storm/stormTrackRules.ts (motion/birth), src/storm/formationData.ts (MIN_ZONE_SCORE), src/storm/config.ts (hail / intensification / evolution), scripts/chmi_radar.py (FCT_AGREE_MAX_DEG), ACTIVE_CONSTANTS v scripts/emit_learning.py",
  "tuneInDays": "Po ~2 dnech bouřek: npm run data:learning-summary && npm run data:propose-calibration → public/data/calibration/proposal.json"
}