{
  "updatedAt": "2026-07-20T14:06:42Z",
  "operaTime": "2026-07-20T14:00:00Z",
  "chmiTime": "2026-07-20T14:05:00Z",
  "opera": true,
  "chmi": true,
  "wind": true,
  "formation": true,
  "sources": {
    "opera": {
      "ok": true,
      "updatedAt": "2026-07-20T14:06:30Z",
      "error": null
    },
    "chmi": {
      "ok": true,
      "updatedAt": "2026-07-20T14:05:00Z",
      "error": null
    },
    "wind": {
      "ok": true,
      "updatedAt": "2026-07-20T13:56:47Z",
      "error": null
    },
    "formation": {
      "ok": true,
      "updatedAt": "2026-07-20T13:56:47Z",
      "error": null
    }
  }
}