{"time": "20260718025500", "frameMinutes": 5, "peaks": [{"id": "cell-13", "trackId": "track-1", "lon": 12.425461407445619, "lat": 49.5927527782045, "maxDbz": 60.5, "trackHeadingDeg": 110.4, "trackSpeedKmh": 37.8, "birthDbz": 55.0, "trueBirth": false, "isNewborn": false, "ageMinutes": 5, "history": [{"time": "20260718025000", "peakLon": 12.384475606903319, "peakLat": 49.60265808280959, "maxDbz": 55.0}, {"time": "20260718025500", "peakLon": 12.425461407445619, "peakLat": 49.5927527782045, "maxDbz": 60.5}]}, {"id": "cell-23", "trackId": "track-2", "lon": 12.22057184055659, "lat": 49.047785770334244, "maxDbz": 60.5, "trackHeadingDeg": null, "trackSpeedKmh": null, "birthDbz": 60.5, "trueBirth": false, "isNewborn": false, "ageMinutes": 0, "history": [{"time": "20260718025500", "peakLon": 12.22057184055659, "peakLat": 49.047785770334244, "maxDbz": 60.5}]}, {"id": "cell-19", "trackId": "track-3", "lon": 11.478796123439098, "lat": 49.37558005319671, "maxDbz": 53.5, "trackHeadingDeg": 0.0, "trackSpeedKmh": 0.0, "birthDbz": 53.5, "trueBirth": false, "isNewborn": false, "ageMinutes": 5, "history": [{"time": "20260718025000", "peakLon": 11.478796123439098, "peakLat": 49.37558005319671, "maxDbz": 53.5}, {"time": "20260718025500", "peakLon": 11.478796123439098, "peakLat": 49.37558005319671, "maxDbz": 53.5}]}, {"id": "cell-14", "trackId": "track-4", "lon": 12.34892274827804, "lat": 49.44134443525733, "maxDbz": 53.0, "trackHeadingDeg": 91.9, "trackSpeedKmh": 23.9, "birthDbz": 49.5, "trueBirth": false, "isNewborn": false, "ageMinutes": 5, "history": [{"time": "20260718025000", "peakLon": 12.321386894183215, "peakLat": 49.44193378893413, "maxDbz": 49.5}, {"time": "20260718025500", "peakLon": 12.34892274827804, "peakLat": 49.44134443525733, "maxDbz": 53.0}]}, {"id": "cell-22", "trackId": "track-5", "lon": 12.183628958675557, "lat": 49.13859961121544, "maxDbz": 50.5, "trackHeadingDeg": 110.2, "trackSpeedKmh": 37.8, "birthDbz": 38.5, "trueBirth": false, "isNewborn": false, "ageMinutes": 5, "history": [{"time": "20260718025000", "peakLon": 12.142976127714334, "peakLat": 49.148415958432906, "maxDbz": 38.5}, {"time": "20260718025500", "peakLon": 12.183628958675557, "peakLat": 49.13859961121544, "maxDbz": 50.5}]}, {"id": "cell-11", "trackId": "track-6", "lon": 12.345674209354339, "lat": 49.657520925312596, "maxDbz": 46.0, "trackHeadingDeg": 101.3, "trackSpeedKmh": 36.4, "birthDbz": 53.5, "trueBirth": false, "isNewborn": false, "ageMinutes": 15, "history": [{"time": "20260718024000", "peakLon": 12.207782963277383, "peakLat": 49.66939035987841, "maxDbz": 53.5}, {"time": "20260718024500", "peakLon": 12.263117639387215, "peakLat": 49.66826131259147, "maxDbz": 49.5}, {"time": "20260718025000", "peakLon": 12.304617045940923, "peakLat": 49.66739619332199, "maxDbz": 45.0}, {"time": "20260718025500", "peakLon": 12.345674209354339, "peakLat": 49.657520925312596, "maxDbz": 46.0}]}, {"id": "cell-10", "trackId": "track-7", "lon": 12.375565797494037, "lat": 49.701896167123486, "maxDbz": 43.0, "trackHeadingDeg": 91.9, "trackSpeedKmh": 29.9, "birthDbz": 39.5, "trueBirth": false, "isNewborn": false, "ageMinutes": 10, "history": [{"time": "20260718024500", "peakLon": 12.306351291055586, "peakLat": 49.703374199056476, "maxDbz": 39.5}, {"time": "20260718025000", "peakLon": 12.347880470285128, "peakLat": 49.70249262198165, "maxDbz": 46.5}, {"time": "20260718025500", "peakLon": 12.375565797494037, "peakLat": 49.701896167123486, "maxDbz": 43.0}]}, {"id": "cell-23", "trackId": "track-8", "lon": 12.108976107253623, "lat": 48.99597701731824, "maxDbz": 43.0, "trackHeadingDeg": 222.8, "trackSpeedKmh": 63.7, "birthDbz": 48.0, "trueBirth": false, "isNewborn": false, "ageMinutes": 10, "history": [{"time": "20260718024500", "peakLon": 12.20772902706391, "peakLat": 49.06606138355628, "maxDbz": 48.0}, {"time": "20260718025500", "peakLon": 12.108976107253623, "peakLat": 48.99597701731824, "maxDbz": 43.0}]}, {"id": "cell-1", "trackId": "track-9", "lon": 16.029059493479163, "lat": 50.93317483295548, "maxDbz": 40.5, "trackHeadingDeg": 49.7, "trackSpeedKmh": 25.4, "birthDbz": 42.0, "trueBirth": false, "isNewborn": false, "ageMinutes": 25, "history": [{"time": "20260718023000", "peakLon": 15.830577227262902, "peakLat": 50.94368451317415, "maxDbz": 42.0}, {"time": "20260718023500", "peakLon": 15.890748284153341, "peakLat": 50.967595657360974, "maxDbz": 46.0}, {"time": "20260718024500", "peakLon": 15.983028878055327, "peakLat": 50.90858131465241, "maxDbz": 37.5}, {"time": "20260718025000", "peakLon": 16.01488499163342, "peakLat": 50.93393716067156, "maxDbz": 39.0}, {"time": "20260718025500", "peakLon": 16.029059493479163, "peakLat": 50.93317483295548, "maxDbz": 40.5}]}, {"id": "cell-3", "trackId": "track-10", "lon": 16.109325630298194, "lat": 50.89273568787824, "maxDbz": 39.5, "trackHeadingDeg": 121.4, "trackSpeedKmh": 62.5, "birthDbz": 47.5, "trueBirth": false, "isNewborn": false, "ageMinutes": 15, "history": [{"time": "20260718024000", "peakLon": 15.919121066124365, "peakLat": 50.966100454110325, "maxDbz": 47.5}, {"time": "20260718025000", "peakLon": 16.053860370502974, "peakLat": 50.90477217394257, "maxDbz": 37.5}, {"time": "20260718025500", "peakLon": 16.109325630298194, "peakLat": 50.89273568787824, "maxDbz": 39.5}]}, {"id": "cell-27", "trackId": "track-11", "lon": 11.728187614012281, "lat": 49.03874778782247, "maxDbz": 38.0, "trackHeadingDeg": 34.9, "trackSpeedKmh": 14.4, "birthDbz": 53.5, "trueBirth": false, "isNewborn": false, "ageMinutes": 25, "history": [{"time": "20260718023000", "peakLon": 11.617438549297786, "peakLat": 48.99543220563346, "maxDbz": 53.5}, {"time": "20260718024000", "peakLon": 11.699933475230463, "peakLat": 49.01217893755504, "maxDbz": 59.5}, {"time": "20260718024500", "peakLon": 11.76752829065987, "peakLat": 48.99308538471555, "maxDbz": 54.0}, {"time": "20260718025500", "peakLon": 11.728187614012281, "peakLat": 49.03874778782247, "maxDbz": 38.0}]}, {"id": "cell-5", "trackId": "track-12", "lon": 12.894754453148135, "lat": 50.490763945576205, "maxDbz": 37.5, "trackHeadingDeg": 80.9, "trackSpeedKmh": 61.0, "birthDbz": 36.5, "trueBirth": true, "isNewborn": true, "ageMinutes": 5, "history": [{"time": "20260718025000", "peakLon": 12.823845812616213, "peakLat": 50.483584997418895, "maxDbz": 36.5}, {"time": "20260718025500", "peakLon": 12.894754453148135, "peakLat": 50.490763945576205, "maxDbz": 37.5}]}, {"id": "cell-20", "trackId": "track-13", "lon": 12.123468396757179, "lat": 49.328905948910986, "maxDbz": 37.5, "trackHeadingDeg": 176.5, "trackSpeedKmh": 44.2, "birthDbz": 54.0, "trueBirth": false, "isNewborn": false, "ageMinutes": 20, "history": [{"time": "20260718023500", "peakLon": 12.058997711386324, "peakLat": 49.429192454682784, "maxDbz": 54.0}, {"time": "20260718024000", "peakLon": 12.114059497507618, "peakLat": 49.42813925430722, "maxDbz": 50.0}, {"time": "20260718024500", "peakLon": 12.086139644399186, "peakLat": 49.41967252778571, "maxDbz": 49.0}, {"time": "20260718025500", "peakLon": 12.123468396757179, "peakLat": 49.328905948910986, "maxDbz": 37.5}]}, {"id": "cell-41", "trackId": "track-14", "lon": 16.630116690637617, "lat": 48.035669702445496, "maxDbz": 37.5, "trackHeadingDeg": null, "trackSpeedKmh": null, "birthDbz": 37.5, "trueBirth": true, "isNewborn": true, "ageMinutes": 0, "history": [{"time": "20260718025500", "peakLon": 16.630116690637617, "peakLat": 48.035669702445496, "maxDbz": 37.5}]}, {"id": "cell-4", "trackId": "track-15", "lon": 12.672148071387996, "lat": 50.54133983410594, "maxDbz": 37.0, "trackHeadingDeg": null, "trackSpeedKmh": null, "birthDbz": 36.0, "trueBirth": true, "isNewborn": true, "ageMinutes": 5, "history": [{"time": "20260718025000", "peakLon": 12.588610184077885, "peakLat": 50.561314624423034, "maxDbz": 36.0}, {"time": "20260718025500", "peakLon": 12.672148071387996, "peakLat": 50.54133983410594, "maxDbz": 37.0}]}, {"id": "cell-33", "trackId": "track-16", "lon": 18.518908380866133, "lat": 48.29025143141938, "maxDbz": 37.0, "trackHeadingDeg": null, "trackSpeedKmh": null, "birthDbz": 37.0, "trueBirth": true, "isNewborn": true, "ageMinutes": 0, "history": [{"time": "20260718025500", "peakLon": 18.518908380866133, "peakLat": 48.29025143141938, "maxDbz": 37.0}]}]}